soft404/__init__.py
soft404/clf.joblib
soft404/convert_to_text.py
soft404/predict.py
soft404/train.py
soft404/utils.py
soft404-0.1.1.dist-info/DESCRIPTION.rst
soft404-0.1.1.dist-info/METADATA
soft404-0.1.1.dist-info/RECORD
soft404-0.1.1.dist-info/WHEEL
soft404-0.1.1.dist-info/metadata.json
soft404-0.1.1.dist-info/top_level.txt
